LICENSE
ethereum_gasprice/__init__.py
ethereum_gasprice/consts.py
ethereum_gasprice/controller/__init__.py
ethereum_gasprice/controller/async_wrapper.py
ethereum_gasprice/controller/base.py
ethereum_gasprice/controller/sync_wrapper.py
ethereum_gasprice/logger.py
ethereum_gasprice/providers/__init__.py
ethereum_gasprice/providers/base.py
ethereum_gasprice/providers/etherchain_provider.py
ethereum_gasprice/providers/etherscan_provider.py
ethereum_gasprice/providers/ethgasstation_provider.py
ethereum_gasprice/providers/poa_provider.py
ethereum_gasprice/providers/web3_provider.py
ethereum_gasprice-1.3.0.dist-info/LICENSE
ethereum_gasprice-1.3.0.dist-info/WHEEL
ethereum_gasprice-1.3.0.dist-info/METADATA
ethereum_gasprice-1.3.0.dist-info/RECORD
