Metadata-Version: 2.1
Name: ethereum-gasprice
Version: 1.3.0
Summary: Tool for fetching actual gasprice in ethereum blockchain
Home-page: https://github.com/Elastoo-Team/ethereum-gasprice-py
License: MIT
Keywords: ethereum,gasprice,web3,etherscan,ethgasstation
Author: Nikita Yugov
Author-email: nikitosnikn@yandex.ru
Requires-Python: >=3.7,<4.0
Classifier: Development Status :: 4 - Beta
Classifier: Environment :: Other Environment
Classifier: Intended Audience :: Developers
Classifier: License :: OSI Approved :: MIT License
Classifier: Operating System :: OS Independent
Classifier: Programming Language :: Python
Classifier: Programming Language :: Python :: 3
Classifier: Programming Language :: Python :: 3.7
Classifier: Programming Language :: Python :: 3.8
Classifier: Programming Language :: Python :: 3.9
Classifier: Topic :: Software Development :: Libraries :: Python Modules
Provides-Extra: web3
Requires-Dist: eth-utils (>=1.0.0)
Requires-Dist: httpx (>=0.10.0,<=1.0.0)
Requires-Dist: web3 (>=5.0.0); extra == "web3"
Project-URL: Documentation, https://ethereum-gasprice.readthedocs.io
Project-URL: Repository, https://github.com/Elastoo-Team/ethereum-gasprice-py
